[
  {
    "case_id": "MEERA_DEMO",
    "case_type": "divorce",
    "city": "pune",
    "total_asset_value_inr": 12800000,
    "children_count": 1,
    "marriage_duration_years": 11,
    "petitioner_age": 34,
    "business_ownership": false,
    "urgency": "medium",
    "complexity_score": 4.2,
    "professional_count": 5,
    "path_taken": "collab",
    "actual_duration_days": 79,
    "actual_cost_inr": 84000,
    "success": true,
    "key_outcome": "Resolved collaboratively \u2014 no court needed",
    "anomaly_flag": false
  },
  {
    "case_id": "SYNTH_00001",
    "case_type": "divorce",
    "city": "delhi",
    "total_asset_value_inr": 4840000,
    "children_count": 1,
    "marriage_duration_years": 25.7,
    "petitioner_age": 28,
    "business_ownership": false,
    "urgency": "medium",
    "complexity_score": 2.44,
    "professional_count": 4,
    "path_taken": "collab",
    "actual_duration_days": 77,
    "actual_cost_inr": 103500,
    "success": true,
    "key_outcome": "Standard resolution according to case parameters",
    "anomaly_flag": false
  },
  {
    "case_id": "SYNTH_00002",
    "case_type": "divorce",
    "city": "hyderabad",
    "total_asset_value_inr": 4080000,
    "children_count": 2,
    "marriage_duration_years": 10.6,
    "petitioner_age": 22,
    "business_ownership": true,
    "urgency": "medium",
    "complexity_score": 3.98,
    "professional_count": 3,
    "path_taken": "med",
    "actual_duration_days": 224,
    "actual_cost_inr": 306500,
    "success": false,
    "key_outcome": "Standard resolution according to case parameters",
    "anomaly_flag": false
  },
  {
    "case_id": "SYNTH_00003",
    "case_type": "divorce",
    "city": "hyderabad",
    "total_asset_value_inr": 26910000,
    "children_count": 1,
    "marriage_duration_years": 1.0,
    "petitioner_age": 36,
    "business_ownership": false,
    "urgency": "high",
    "complexity_score": 4.07,
    "professional_count": 5,
    "path_taken": "med",
    "actual_duration_days": 137,
    "actual_cost_inr": 284000,
    "success": true,
    "key_outcome": "Standard resolution according to case parameters",
    "anomaly_flag": false
  },
  {
    "case_id": "SYNTH_00004",
    "case_type": "divorce",
    "city": "hyderabad",
    "total_asset_value_inr": 1400000,
    "children_count": 0,
    "marriage_duration_years": 11.9,
    "petitioner_age": 33,
    "business_ownership": true,
    "urgency": "high",
    "complexity_score": 3.25,
    "professional_count": 5,
    "path_taken": "collab",
    "actual_duration_days": 142,
    "actual_cost_inr": 132000,
    "success": true,
    "key_outcome": "Standard resolution according to case parameters",
    "anomaly_flag": false
  },
  {
    "case_id": "SYNTH_00005",
    "case_type": "inheritance",
    "city": "delhi",
    "total_asset_value_inr": 7020000,
    "children_count": 0,
    "marriage_duration_years": 0.0,
    "petitioner_age": 43,
    "business_ownership": false,
    "urgency": "medium",
    "complexity_score": 1.4,
    "professional_count": 3,
    "path_taken": "collab",
    "actual_duration_days": 50,
    "actual_cost_inr": 84000,
    "success": true,
    "key_outcome": "Standard resolution according to case parameters",
    "anomaly_flag": false
  },
  {
    "case_id": "SYNTH_00006",
    "case_type": "divorce",
    "city": "delhi",
    "total_asset_value_inr": 15590000,
    "children_count": 1,
    "marriage_duration_years": 14.6,
    "petitioner_age": 48,
    "business_ownership": false,
    "urgency": "low",
    "complexity_score": 3.07,
    "professional_count": 5,
    "path_taken": "collab",
    "actual_duration_days": 76,
    "actual_cost_inr": 72500,
    "success": true,
    "key_outcome": "Standard resolution according to case parameters",
    "anomaly_flag": false
  },
  {
    "case_id": "SYNTH_00007",
    "case_type": "divorce",
    "city": "delhi",
    "total_asset_value_inr": 10990000,
    "children_count": 1,
    "marriage_duration_years": 8.2,
    "petitioner_age": 44,
    "business_ownership": false,
    "urgency": "low",
    "complexity_score": 2.89,
    "professional_count": 7,
    "path_taken": "collab",
    "actual_duration_days": 46,
    "actual_cost_inr": 104500,
    "success": true,
    "key_outcome": "Standard resolution according to case parameters",
    "anomaly_flag": false
  },
  {
    "case_id": "SYNTH_00008",
    "case_type": "inheritance",
    "city": "ahmedabad",
    "total_asset_value_inr": 9630000,
    "children_count": 0,
    "marriage_duration_years": 0.0,
    "petitioner_age": 37,
    "business_ownership": false,
    "urgency": "low",
    "complexity_score": 1.41,
    "professional_count": 4,
    "path_taken": "collab",
    "actual_duration_days": 121,
    "actual_cost_inr": 97000,
    "success": true,
    "key_outcome": "Standard resolution according to case parameters",
    "anomaly_flag": false
  },
  {
    "case_id": "SYNTH_00009",
    "case_type": "divorce",
    "city": "mumbai",
    "total_asset_value_inr": 23440000,
    "children_count": 0,
    "marriage_duration_years": 0.5,
    "petitioner_age": 34,
    "business_ownership": true,
    "urgency": "medium",
    "complexity_score": 4.63,
    "professional_count": 3,
    "path_taken": "med",
    "actual_duration_days": 240,
    "actual_cost_inr": 906500,
    "success": true,
    "key_outcome": "Standard resolution according to case parameters",
    "anomaly_flag": false
  },
  {
    "case_id": "SYNTH_00010",
    "case_type": "divorce",
    "city": "mumbai",
    "total_asset_value_inr": 49900000,
    "children_count": 1,
    "marriage_duration_years": 12.3,
    "petitioner_age": 44,
    "business_ownership": false,
    "urgency": "low",
    "complexity_score": 3.8,
    "professional_count": 4,
    "path_taken": "med",
    "actual_duration_days": 121,
    "actual_cost_inr": 392500,
    "success": true,
    "key_outcome": "Standard resolution according to case parameters",
    "anomaly_flag": false
  },
  {
    "case_id": "SYNTH_00011",
    "case_type": "divorce",
    "city": "delhi",
    "total_asset_value_inr": 24580000,
    "children_count": 0,
    "marriage_duration_years": 8.5,
    "petitioner_age": 40,
    "business_ownership": true,
    "urgency": "medium",
    "complexity_score": 4.49,
    "professional_count": 4,
    "path_taken": "med",
    "actual_duration_days": 472,
    "actual_cost_inr": 373000,
    "success": true,
    "key_outcome": "Standard resolution according to case parameters",
    "anomaly_flag": false
  },
  {
    "case_id": "SYNTH_00012",
    "case_type": "property",
    "city": "hyderabad",
    "total_asset_value_inr": 5470000,
    "children_count": 0,
    "marriage_duration_years": 0.0,
    "petitioner_age": 41,
    "business_ownership": false,
    "urgency": "high",
    "complexity_score": 2.24,
    "professional_count": 3,
    "path_taken": "collab",
    "actual_duration_days": 138,
    "actual_cost_inr": 66500,
    "success": true,
    "key_outcome": "Standard resolution according to case parameters",
    "anomaly_flag": false
  },
  {
    "case_id": "SYNTH_00013",
    "case_type": "business",
    "city": "ahmedabad",
    "total_asset_value_inr": 5490000,
    "children_count": 0,
    "marriage_duration_years": 0.0,
    "petitioner_age": 21,
    "business_ownership": true,
    "urgency": "medium",
    "complexity_score": 2.84,
    "professional_count": 5,
    "path_taken": "med",
    "actual_duration_days": 119,
    "actual_cost_inr": 327000,
    "success": false,
    "key_outcome": "Standard resolution according to case parameters",
    "anomaly_flag": false
  },
  {
    "case_id": "SYNTH_00014",
    "case_type": "business",
    "city": "ahmedabad",
    "total_asset_value_inr": 1800000,
    "children_count": 0,
    "marriage_duration_years": 0.0,
    "petitioner_age": 32,
    "business_ownership": true,
    "urgency": "high",
    "complexity_score": 3.21,
    "professional_count": 5,
    "path_taken": "collab",
    "actual_duration_days": 101,
    "actual_cost_inr": 110000,
    "success": true,
    "key_outcome": "Standard resolution according to case parameters",
    "anomaly_flag": false
  },
  {
    "case_id": "SYNTH_00015",
    "case_type": "nri",
    "city": "bangalore",
    "total_asset_value_inr": 6430000,
    "children_count": 0,
    "marriage_duration_years": 0.0,
    "petitioner_age": 55,
    "business_ownership": false,
    "urgency": "medium",
    "complexity_score": 3.99,
    "professional_count": 5,
    "path_taken": "med",
    "actual_duration_days": 146,
    "actual_cost_inr": 1098500,
    "success": false,
    "key_outcome": "Standard resolution according to case parameters",
    "anomaly_flag": false
  },
  {
    "case_id": "SYNTH_00016",
    "case_type": "property",
    "city": "mumbai",
    "total_asset_value_inr": 6730000,
    "children_count": 0,
    "marriage_duration_years": 0.0,
    "petitioner_age": 39,
    "business_ownership": false,
    "urgency": "low",
    "complexity_score": 2.07,
    "professional_count": 3,
    "path_taken": "collab",
    "actual_duration_days": 46,
    "actual_cost_inr": 76000,
    "success": true,
    "key_outcome": "Standard resolution according to case parameters",
    "anomaly_flag": false
  },
  {
    "case_id": "SYNTH_00017",
    "case_type": "inheritance",
    "city": "bangalore",
    "total_asset_value_inr": 24660000,
    "children_count": 0,
    "marriage_duration_years": 0.0,
    "petitioner_age": 38,
    "business_ownership": false,
    "urgency": "high",
    "complexity_score": 3.59,
    "professional_count": 3,
    "path_taken": "med",
    "actual_duration_days": 253,
    "actual_cost_inr": 343500,
    "success": false,
    "key_outcome": "Standard resolution according to case parameters",
    "anomaly_flag": false
  },
  {
    "case_id": "SYNTH_00018",
    "case_type": "divorce",
    "city": "bangalore",
    "total_asset_value_inr": 24140000,
    "children_count": 0,
    "marriage_duration_years": 0.9,
    "petitioner_age": 43,
    "business_ownership": true,
    "urgency": "critical",
    "complexity_score": 5.45,
    "professional_count": 3,
    "path_taken": "med",
    "actual_duration_days": 233,
    "actual_cost_inr": 312500,
    "success": false,
    "key_outcome": "Standard resolution according to case parameters",
    "anomaly_flag": false
  },
  {
    "case_id": "SYNTH_00019",
    "case_type": "divorce",
    "city": "chennai",
    "total_asset_value_inr": 5510000,
    "children_count": 2,
    "marriage_duration_years": 8.1,
    "petitioner_age": 44,
    "business_ownership": false,
    "urgency": "high",
    "complexity_score": 2.75,
    "professional_count": 2,
    "path_taken": "collab",
    "actual_duration_days": 143,
    "actual_cost_inr": 149000,
    "success": true,
    "key_outcome": "Standard resolution according to case parameters",
    "anomaly_flag": false
  },
  {
    "case_id": "SYNTH_00020",
    "case_type": "property",
    "city": "bangalore",
    "total_asset_value_inr": 31950000,
    "children_count": 0,
    "marriage_duration_years": 0.0,
    "petitioner_age": 44,
    "business_ownership": false,
    "urgency": "low",
    "complexity_score": 2.68,
    "professional_count": 4,
    "path_taken": "collab",
    "actual_duration_days": 82,
    "actual_cost_inr": 182500,
    "success": true,
    "key_outcome": "Standard resolution according to case parameters",
    "anomaly_flag": false
  },
  {
    "case_id": "SYNTH_00021",
    "case_type": "divorce",
    "city": "ahmedabad",
    "total_asset_value_inr": 12730000,
    "children_count": 0,
    "marriage_duration_years": 10.4,
    "petitioner_age": 31,
    "business_ownership": false,
    "urgency": "low",
    "complexity_score": 1.7,
    "professional_count": 5,
    "path_taken": "collab",
    "actual_duration_days": 68,
    "actual_cost_inr": 65000,
    "success": true,
    "key_outcome": "Standard resolution according to case parameters",
    "anomaly_flag": false
  },
  {
    "case_id": "SYNTH_00022",
    "case_type": "divorce",
    "city": "ahmedabad",
    "total_asset_value_inr": 3400000,
    "children_count": 2,
    "marriage_duration_years": 0.5,
    "petitioner_age": 44,
    "business_ownership": false,
    "urgency": "medium",
    "complexity_score": 2.35,
    "professional_count": 3,
    "path_taken": "collab",
    "actual_duration_days": 65,
    "actual_cost_inr": 92500,
    "success": true,
    "key_outcome": "Standard resolution according to case parameters",
    "anomaly_flag": false
  },
  {
    "case_id": "SYNTH_00023",
    "case_type": "property",
    "city": "bangalore",
    "total_asset_value_inr": 22970000,
    "children_count": 0,
    "marriage_duration_years": 0.0,
    "petitioner_age": 45,
    "business_ownership": false,
    "urgency": "medium",
    "complexity_score": 2.9,
    "professional_count": 2,
    "path_taken": "collab",
    "actual_duration_days": 104,
    "actual_cost_inr": 154000,
    "success": true,
    "key_outcome": "Standard resolution according to case parameters",
    "anomaly_flag": false
  },
  {
    "case_id": "SYNTH_00024",
    "case_type": "property",
    "city": "mumbai",
    "total_asset_value_inr": 11370000,
    "children_count": 0,
    "marriage_duration_years": 0.0,
    "petitioner_age": 29,
    "business_ownership": false,
    "urgency": "medium",
    "complexity_score": 2.12,
    "professional_count": 4,
    "path_taken": "collab",
    "actual_duration_days": 56,
    "actual_cost_inr": 83000,
    "success": true,
    "key_outcome": "Standard resolution according to case parameters",
    "anomaly_flag": false
  },
  {
    "case_id": "SYNTH_00025",
    "case_type": "business",
    "city": "mumbai",
    "total_asset_value_inr": 12580000,
    "children_count": 0,
    "marriage_duration_years": 0.0,
    "petitioner_age": 21,
    "business_ownership": true,
    "urgency": "medium",
    "complexity_score": 4.23,
    "professional_count": 4,
    "path_taken": "med",
    "actual_duration_days": 241,
    "actual_cost_inr": 272000,
    "success": false,
    "key_outcome": "Standard resolution according to case parameters",
    "anomaly_flag": false
  },
  {
    "case_id": "SYNTH_00026",
    "case_type": "divorce",
    "city": "delhi",
    "total_asset_value_inr": 6400000,
    "children_count": 1,
    "marriage_duration_years": 0.5,
    "petitioner_age": 50,
    "business_ownership": false,
    "urgency": "high",
    "complexity_score": 2.45,
    "professional_count": 6,
    "path_taken": "med",
    "actual_duration_days": 122,
    "actual_cost_inr": 161500,
    "success": true,
    "key_outcome": "Standard resolution according to case parameters",
    "anomaly_flag": false
  },
  {
    "case_id": "SYNTH_00027",
    "case_type": "inheritance",
    "city": "mumbai",
    "total_asset_value_inr": 13380000,
    "children_count": 0,
    "marriage_duration_years": 0.0,
    "petitioner_age": 37,
    "business_ownership": true,
    "urgency": "medium",
    "complexity_score": 3.69,
    "professional_count": 3,
    "path_taken": "med",
    "actual_duration_days": 206,
    "actual_cost_inr": 517500,
    "success": false,
    "key_outcome": "Standard resolution according to case parameters",
    "anomaly_flag": false
  },
  {
    "case_id": "SYNTH_00029",
    "case_type": "divorce",
    "city": "pune",
    "total_asset_value_inr": 2080000,
    "children_count": 1,
    "marriage_duration_years": 6.4,
    "petitioner_age": 47,
    "business_ownership": false,
    "urgency": "low",
    "complexity_score": 1.79,
    "professional_count": 4,
    "path_taken": "collab",
    "actual_duration_days": 102,
    "actual_cost_inr": 77000,
    "success": true,
    "key_outcome": "Standard resolution according to case parameters",
    "anomaly_flag": false
  },
  {
    "case_id": "SYNTH_00030",
    "case_type": "inheritance",
    "city": "pune",
    "total_asset_value_inr": 3880000,
    "children_count": 0,
    "marriage_duration_years": 0.0,
    "petitioner_age": 21,
    "business_ownership": false,
    "urgency": "low",
    "complexity_score": 1.36,
    "professional_count": 3,
    "path_taken": "collab",
    "actual_duration_days": 46,
    "actual_cost_inr": 87500,
    "success": true,
    "key_outcome": "Standard resolution according to case parameters",
    "anomaly_flag": false
  },
  {
    "case_id": "SYNTH_00031",
    "case_type": "property",
    "city": "mumbai",
    "total_asset_value_inr": 57780000,
    "children_count": 0,
    "marriage_duration_years": 0.0,
    "petitioner_age": 45,
    "business_ownership": false,
    "urgency": "low",
    "complexity_score": 3.71,
    "professional_count": 3,
    "path_taken": "med",
    "actual_duration_days": 339,
    "actual_cost_inr": 288500,
    "success": false,
    "key_outcome": "Standard resolution according to case parameters",
    "anomaly_flag": false
  },
  {
    "case_id": "SYNTH_00032",
    "case_type": "property",
    "city": "delhi",
    "total_asset_value_inr": 14280000,
    "children_count": 0,
    "marriage_duration_years": 0.0,
    "petitioner_age": 43,
    "business_ownership": true,
    "urgency": "medium",
    "complexity_score": 4.02,
    "professional_count": 2,
    "path_taken": "court",
    "actual_duration_days": 1359,
    "actual_cost_inr": 981000,
    "success": false,
    "key_outcome": "Standard resolution according to case parameters",
    "anomaly_flag": false
  },
  {
    "case_id": "SYNTH_00034",
    "case_type": "business",
    "city": "bangalore",
    "total_asset_value_inr": 12360000,
    "children_count": 0,
    "marriage_duration_years": 0.0,
    "petitioner_age": 34,
    "business_ownership": true,
    "urgency": "medium",
    "complexity_score": 3.79,
    "professional_count": 4,
    "path_taken": "med",
    "actual_duration_days": 262,
    "actual_cost_inr": 338500,
    "success": false,
    "key_outcome": "Standard resolution according to case parameters",
    "anomaly_flag": false
  },
  {
    "case_id": "SYNTH_00035",
    "case_type": "inheritance",
    "city": "mumbai",
    "total_asset_value_inr": 30960000,
    "children_count": 0,
    "marriage_duration_years": 0.0,
    "petitioner_age": 41,
    "business_ownership": false,
    "urgency": "high",
    "complexity_score": 3.06,
    "professional_count": 3,
    "path_taken": "collab",
    "actual_duration_days": 46,
    "actual_cost_inr": 69000,
    "success": true,
    "key_outcome": "Standard resolution according to case parameters",
    "anomaly_flag": false
  },
  {
    "case_id": "SYNTH_00036",
    "case_type": "property",
    "city": "hyderabad",
    "total_asset_value_inr": 14850000,
    "children_count": 0,
    "marriage_duration_years": 0.0,
    "petitioner_age": 40,
    "business_ownership": false,
    "urgency": "medium",
    "complexity_score": 2.55,
    "professional_count": 4,
    "path_taken": "court",
    "actual_duration_days": 1073,
    "actual_cost_inr": 612500,
    "success": false,
    "key_outcome": "Standard resolution according to case parameters",
    "anomaly_flag": false
  },
  {
    "case_id": "SYNTH_00037",
    "case_type": "divorce",
    "city": "pune",
    "total_asset_value_inr": 7170000,
    "children_count": 1,
    "marriage_duration_years": 13.6,
    "petitioner_age": 38,
    "business_ownership": false,
    "urgency": "medium",
    "complexity_score": 2.07,
    "professional_count": 4,
    "path_taken": "collab",
    "actual_duration_days": 106,
    "actual_cost_inr": 94000,
    "success": true,
    "key_outcome": "Standard resolution according to case parameters",
    "anomaly_flag": false
  },
  {
    "case_id": "SYNTH_00039",
    "case_type": "property",
    "city": "hyderabad",
    "total_asset_value_inr": 21580000,
    "children_count": 0,
    "marriage_duration_years": 0.0,
    "petitioner_age": 43,
    "business_ownership": false,
    "urgency": "medium",
    "complexity_score": 2.6,
    "professional_count": 3,
    "path_taken": "court",
    "actual_duration_days": 553,
    "actual_cost_inr": 742500,
    "success": false,
    "key_outcome": "Standard resolution according to case parameters",
    "anomaly_flag": false
  },
  {
    "case_id": "SYNTH_00041",
    "case_type": "inheritance",
    "city": "chennai",
    "total_asset_value_inr": 5840000,
    "children_count": 0,
    "marriage_duration_years": 0.0,
    "petitioner_age": 45,
    "business_ownership": true,
    "urgency": "medium",
    "complexity_score": 3.49,
    "professional_count": 3,
    "path_taken": "collab",
    "actual_duration_days": 86,
    "actual_cost_inr": 159000,
    "success": true,
    "key_outcome": "Standard resolution according to case parameters",
    "anomaly_flag": false
  },
  {
    "case_id": "SYNTH_00042",
    "case_type": "divorce",
    "city": "pune",
    "total_asset_value_inr": 2950000,
    "children_count": 2,
    "marriage_duration_years": 0.5,
    "petitioner_age": 34,
    "business_ownership": false,
    "urgency": "low",
    "complexity_score": 1.83,
    "professional_count": 3,
    "path_taken": "collab",
    "actual_duration_days": 148,
    "actual_cost_inr": 129000,
    "success": true,
    "key_outcome": "Standard resolution according to case parameters",
    "anomaly_flag": false
  },
  {
    "case_id": "SYNTH_00044",
    "case_type": "divorce",
    "city": "chennai",
    "total_asset_value_inr": 6870000,
    "children_count": 0,
    "marriage_duration_years": 12.2,
    "petitioner_age": 47,
    "business_ownership": false,
    "urgency": "high",
    "complexity_score": 1.99,
    "professional_count": 4,
    "path_taken": "collab",
    "actual_duration_days": 73,
    "actual_cost_inr": 82000,
    "success": true,
    "key_outcome": "Standard resolution according to case parameters",
    "anomaly_flag": false
  },
  {
    "case_id": "SYNTH_00045",
    "case_type": "divorce",
    "city": "pune",
    "total_asset_value_inr": 38620000,
    "children_count": 1,
    "marriage_duration_years": 16.7,
    "petitioner_age": 36,
    "business_ownership": false,
    "urgency": "high",
    "complexity_score": 4.59,
    "professional_count": 5,
    "path_taken": "med",
    "actual_duration_days": 257,
    "actual_cost_inr": 279500,
    "success": true,
    "key_outcome": "Standard resolution according to case parameters",
    "anomaly_flag": false
  },
  {
    "case_id": "SYNTH_00047",
    "case_type": "inheritance",
    "city": "bangalore",
    "total_asset_value_inr": 19990000,
    "children_count": 0,
    "marriage_duration_years": 0.0,
    "petitioner_age": 41,
    "business_ownership": false,
    "urgency": "medium",
    "complexity_score": 2.32,
    "professional_count": 3,
    "path_taken": "collab",
    "actual_duration_days": 56,
    "actual_cost_inr": 86500,
    "success": true,
    "key_outcome": "Standard resolution according to case parameters",
    "anomaly_flag": false
  },
  {
    "case_id": "SYNTH_00050",
    "case_type": "divorce",
    "city": "chennai",
    "total_asset_value_inr": 3610000,
    "children_count": 0,
    "marriage_duration_years": 11.2,
    "petitioner_age": 30,
    "business_ownership": false,
    "urgency": "low",
    "complexity_score": 1.4,
    "professional_count": 2,
    "path_taken": "collab",
    "actual_duration_days": 90,
    "actual_cost_inr": 44000,
    "success": true,
    "key_outcome": "Standard resolution according to case parameters",
    "anomaly_flag": false
  },
  {
    "case_id": "SYNTH_00053",
    "case_type": "divorce",
    "city": "bangalore",
    "total_asset_value_inr": 9650000,
    "children_count": 0,
    "marriage_duration_years": 10.2,
    "petitioner_age": 31,
    "business_ownership": true,
    "urgency": "medium",
    "complexity_score": 3.18,
    "professional_count": 5,
    "path_taken": "court",
    "actual_duration_days": 230,
    "actual_cost_inr": 445500,
    "success": false,
    "key_outcome": "Standard resolution according to case parameters",
    "anomaly_flag": false
  },
  {
    "case_id": "SYNTH_00067",
    "case_type": "business",
    "city": "bangalore",
    "total_asset_value_inr": 25260000,
    "children_count": 0,
    "marriage_duration_years": 0.0,
    "petitioner_age": 40,
    "business_ownership": true,
    "urgency": "low",
    "complexity_score": 4.47,
    "professional_count": 7,
    "path_taken": "med",
    "actual_duration_days": 278,
    "actual_cost_inr": 479500,
    "success": false,
    "key_outcome": "Standard resolution according to case parameters",
    "anomaly_flag": false
  },
  {
    "case_id": "SYNTH_00076",
    "case_type": "divorce",
    "city": "delhi",
    "total_asset_value_inr": 8590000,
    "children_count": 3,
    "marriage_duration_years": 9.5,
    "petitioner_age": 25,
    "business_ownership": false,
    "urgency": "medium",
    "complexity_score": 3.2,
    "professional_count": 3,
    "path_taken": "court",
    "actual_duration_days": 666,
    "actual_cost_inr": 777000,
    "success": false,
    "key_outcome": "Standard resolution according to case parameters",
    "anomaly_flag": false
  },
  {
    "case_id": "SYNTH_00083",
    "case_type": "nri",
    "city": "mumbai",
    "total_asset_value_inr": 5720000,
    "children_count": 0,
    "marriage_duration_years": 0.0,
    "petitioner_age": 50,
    "business_ownership": false,
    "urgency": "medium",
    "complexity_score": 4.07,
    "professional_count": 6,
    "path_taken": "med",
    "actual_duration_days": 376,
    "actual_cost_inr": 1110000,
    "success": false,
    "key_outcome": "Standard resolution according to case parameters",
    "anomaly_flag": false
  },
  {
    "case_id": "SYNTH_00085",
    "case_type": "divorce",
    "city": "chennai",
    "total_asset_value_inr": 7240000,
    "children_count": 1,
    "marriage_duration_years": 3.6,
    "petitioner_age": 27,
    "business_ownership": false,
    "urgency": "low",
    "complexity_score": 2.2,
    "professional_count": 4,
    "path_taken": "collab",
    "actual_duration_days": 46,
    "actual_cost_inr": 109500,
    "success": true,
    "key_outcome": "Standard resolution according to case parameters",
    "anomaly_flag": false
  },
  {
    "case_id": "SYNTH_00092",
    "case_type": "property",
    "city": "ahmedabad",
    "total_asset_value_inr": 25330000,
    "children_count": 0,
    "marriage_duration_years": 0.0,
    "petitioner_age": 34,
    "business_ownership": true,
    "urgency": "high",
    "complexity_score": 5.34,
    "professional_count": 4,
    "path_taken": "court",
    "actual_duration_days": 1135,
    "actual_cost_inr": 1975000,
    "success": false,
    "key_outcome": "Standard resolution according to case parameters",
    "anomaly_flag": false
  },
  {
    "case_id": "SYNTH_00095",
    "case_type": "divorce",
    "city": "delhi",
    "total_asset_value_inr": 8370000,
    "children_count": 0,
    "marriage_duration_years": 19.3,
    "petitioner_age": 40,
    "business_ownership": false,
    "urgency": "medium",
    "complexity_score": 1.79,
    "professional_count": 3,
    "path_taken": "court",
    "actual_duration_days": 224,
    "actual_cost_inr": 788000,
    "success": true,
    "key_outcome": "Standard resolution according to case parameters",
    "anomaly_flag": false
  }
]